setup.py
cool_ascii_faces.egg-info/PKG-INFO
cool_ascii_faces.egg-info/SOURCES.txt
cool_ascii_faces.egg-info/dependency_links.txt
cool_ascii_faces.egg-info/entry_points.txt
cool_ascii_faces.egg-info/top_level.txt
cool_ascii_faces.egg-info/zip-safe
coolasciifaces/__init__.py
coolasciifaces/cli.py