Metadata-Version: 1.1
Name: cool-ascii-faces
Version: 0.0.1
Summary: get some cool ascii faces
Home-page: https://github.com/vape/cool-ascii-faces
Author: Taylan Aydinli
Author-email: taylanaydinli@gmail.com
License: MIT
Platform: UNKNOWN
Classifier: Development Status :: 4 - Beta
Classifier: Intended Audience :: Developers
Classifier: Intended Audience :: End Users/Desktop
Classifier: License :: OSI Approved :: MIT License
Classifier: Operating System :: POSIX
Classifier: Operating System :: MacOS
Classifier: Operating System :: Unix
Classifier: Operating System :: Microsoft :: Windows
Classifier: Programming Language :: Python
Classifier: Topic :: Software Development :: Libraries :: Python Modules
